{
  "source": {
    "sourceType": "property_record",
    "system": "GWorks Public Access",
    "displayCitation": "Gage County Assessor GWorks property report",
    "county": "Gage County",
    "reportName": "Gage County Assessor property report",
    "recordType": "GWORKS_PROPERTY_REPORT",
    "printedAt": null,
    "sourceImages": [],
    "sourceImageLinks": [],
    "notes": "Generated from GWorks PDF facts, with 2019-and-newer tax-statement history, assessed valuation components, credit breakdowns, payment status, and levy distributions added from Nebraska Taxes Online detail captures. The GWorks export does not expose Marshall & Swift cost-source, base-cost, adjustment, depreciation, or RCNLD detail."
  },
  "guidedSnapshot": {
    "snapshotYear": 2025,
    "latestFinalTaxYear": 2025,
    "assets": {
      "photo": null,
      "sketch": null,
      "additionalPhotos": []
    },
    "parcel": {
      "parcelId": "0003273100",
      "mapNumber": "3273100",
      "stateGeoCode": "4407-05-3-00000-000-0000",
      "owner": "FRERICHS, LARRY L TRUSTEE",
      "mailingAddress": null,
      "situsAddress": "Tax District: 75",
      "countyName": "GAGE",
      "taxDistrict": "75",
      "schoolDistrict": "SCHOOL 1 WYMORE, 34-0001",
      "accountType": "Agricultural",
      "legalDescription": "5 2 8 SEC 5-2-8 SW 160.00 AC"
    },
    "classification": {
      "status": "Unimproved",
      "location": "Rural",
      "propertyClass": "Agricultural",
      "citySize": "No Population",
      "zoning": "Agricultural",
      "lotSize": "N/A"
    },
    "residential": null,
    "taxpayerHistory": [
      {
        "year": 2025,
        "assessedValue": 664185,
        "taxes": 6538.18,
        "status": "partially-paid",
        "assessmentSource": "Nebraska Taxes Online detail modal"
      },
      {
        "year": 2024,
        "assessedValue": 477385,
        "taxes": 5200.6,
        "status": "tax-statement",
        "assessmentSource": "Nebraska Taxes Online detail modal"
      },
      {
        "year": 2023,
        "assessedValue": 407595,
        "taxes": 6137.06,
        "status": "tax-statement",
        "assessmentSource": "Nebraska Taxes Online detail modal"
      },
      {
        "year": 2022,
        "assessedValue": 372985,
        "taxes": 5815.68,
        "status": "tax-statement",
        "assessmentSource": "Nebraska Taxes Online detail modal"
      },
      {
        "year": 2021,
        "assessedValue": 372985,
        "taxes": 5941.82,
        "status": "tax-statement",
        "assessmentSource": "Nebraska Taxes Online detail modal"
      },
      {
        "year": 2020,
        "assessedValue": 372985,
        "taxes": 5966.6,
        "status": "tax-statement",
        "assessmentSource": "Nebraska Taxes Online detail modal"
      },
      {
        "year": 2019,
        "assessedValue": 392700,
        "taxes": 6387.56,
        "status": "tax-statement",
        "assessmentSource": "Nebraska Taxes Online detail modal"
      }
    ],
    "taxStatements": [
      {
        "taxYear": 2025,
        "statementNumber": "4625",
        "statementType": "REAL",
        "totalTaxesDue": 6538.18,
        "dueDate": null,
        "assessedValue": 664185,
        "grossTaxAmount": 9287.72,
        "credits": {
          "homestead": {
            "value": 0,
            "amount": 0
          },
          "nonAgTax": {
            "value": null,
            "amount": 0
          },
          "agLandTax": {
            "value": null,
            "amount": 0
          },
          "schoolTax": {
            "value": null,
            "amount": -1801.14
          }
        },
        "netAmountDue": 6538.18,
        "totalPaid": 3269.09,
        "taxDue": 3269.09,
        "derived": {
          "grossLevyRate": 0.013983639999999999,
          "netEffectiveTaxRate": 0.009843913969752404,
          "totalCreditAmount": -2749.54
        },
        "sourceNote": "Nebraska Taxes Online statement detail modal.",
        "land": 407595,
        "dwelling": 0,
        "outbuilding": 0
      },
      {
        "taxYear": 2024,
        "statementNumber": "5391",
        "statementType": "REAL",
        "totalTaxesDue": 5200.6,
        "dueDate": null,
        "assessedValue": 477385,
        "grossTaxAmount": 7111.3,
        "credits": {
          "homestead": {
            "value": 0,
            "amount": 0
          },
          "nonAgTax": {
            "value": null,
            "amount": 0
          },
          "agLandTax": {
            "value": null,
            "amount": 0
          },
          "schoolTax": {
            "value": null,
            "amount": -1224.32
          }
        },
        "netAmountDue": 5200.6,
        "totalPaid": 5200.6,
        "taxDue": 0,
        "derived": {
          "grossLevyRate": 0.014896359999999999,
          "netEffectiveTaxRate": 0.010893932570147785,
          "totalCreditAmount": -1910.7
        },
        "sourceNote": "Nebraska Taxes Online statement detail modal.",
        "land": null,
        "dwelling": null,
        "outbuilding": 0
      },
      {
        "taxYear": 2023,
        "statementNumber": "5378",
        "statementType": "REAL",
        "totalTaxesDue": 6137.06,
        "dueDate": null,
        "assessedValue": 407595,
        "grossTaxAmount": 6681.4,
        "credits": {
          "homestead": {
            "value": 0,
            "amount": 0
          },
          "nonAgTax": {
            "value": null,
            "amount": 0
          },
          "agLandTax": {
            "value": null,
            "amount": 0
          },
          "schoolTax": {
            "value": null,
            "amount": 0
          }
        },
        "netAmountDue": 6137.06,
        "totalPaid": 6137.06,
        "taxDue": 0,
        "derived": {
          "grossLevyRate": 0.01639225,
          "netEffectiveTaxRate": 0.015056759773795067,
          "totalCreditAmount": -544.34
        },
        "sourceNote": "Nebraska Taxes Online statement detail modal.",
        "land": null,
        "dwelling": null,
        "outbuilding": 0
      },
      {
        "taxYear": 2022,
        "statementNumber": "3904",
        "statementType": "REAL",
        "totalTaxesDue": 5815.68,
        "dueDate": null,
        "assessedValue": 372985,
        "grossTaxAmount": 6292.7,
        "credits": {
          "homestead": {
            "value": 0,
            "amount": 0
          },
          "nonAgTax": {
            "value": null,
            "amount": 0
          },
          "agLandTax": {
            "value": null,
            "amount": 0
          },
          "schoolTax": {
            "value": null,
            "amount": 0
          }
        },
        "netAmountDue": 5815.68,
        "totalPaid": 5815.68,
        "taxDue": 0,
        "derived": {
          "grossLevyRate": 0.01687121,
          "netEffectiveTaxRate": 0.015592262423421854,
          "totalCreditAmount": -477.02
        },
        "sourceNote": "Nebraska Taxes Online statement detail modal.",
        "land": null,
        "dwelling": null,
        "outbuilding": 0
      },
      {
        "taxYear": 2021,
        "statementNumber": "3894",
        "statementType": "REAL",
        "totalTaxesDue": 5941.82,
        "dueDate": null,
        "assessedValue": 372985,
        "grossTaxAmount": 6423.16,
        "credits": {
          "homestead": {
            "value": 0,
            "amount": 0
          },
          "nonAgTax": {
            "value": null,
            "amount": 0
          },
          "agLandTax": {
            "value": null,
            "amount": 0
          },
          "schoolTax": {
            "value": null,
            "amount": 0
          }
        },
        "netAmountDue": 5941.82,
        "totalPaid": 5941.82,
        "taxDue": 0,
        "derived": {
          "grossLevyRate": 0.01722094,
          "netEffectiveTaxRate": 0.015930452967277502,
          "totalCreditAmount": -481.34
        },
        "sourceNote": "Nebraska Taxes Online statement detail modal.",
        "land": null,
        "dwelling": null,
        "outbuilding": 0
      },
      {
        "taxYear": 2020,
        "statementNumber": "3874",
        "statementType": "REAL",
        "totalTaxesDue": 5966.6,
        "dueDate": null,
        "assessedValue": 372985,
        "grossTaxAmount": 6424.02,
        "credits": {
          "homestead": {
            "value": 0,
            "amount": 0
          },
          "nonAgTax": {
            "value": null,
            "amount": 0
          },
          "agLandTax": {
            "value": null,
            "amount": 0
          },
          "schoolTax": {
            "value": null,
            "amount": 0
          }
        },
        "netAmountDue": 5966.6,
        "totalPaid": 5966.6,
        "taxDue": 0,
        "derived": {
          "grossLevyRate": 0.01722327,
          "netEffectiveTaxRate": 0.015996889955360135,
          "totalCreditAmount": -457.42
        },
        "sourceNote": "Nebraska Taxes Online statement detail modal.",
        "land": null,
        "dwelling": null,
        "outbuilding": 0
      },
      {
        "taxYear": 2019,
        "statementNumber": "3862",
        "statementType": "REAL",
        "totalTaxesDue": 6387.56,
        "dueDate": null,
        "assessedValue": 392700,
        "grossTaxAmount": 6878.36,
        "credits": {
          "homestead": {
            "value": 0,
            "amount": 0
          },
          "nonAgTax": {
            "value": null,
            "amount": 0
          },
          "agLandTax": {
            "value": null,
            "amount": 0
          },
          "schoolTax": {
            "value": null,
            "amount": 0
          }
        },
        "netAmountDue": 6387.56,
        "totalPaid": 6387.56,
        "taxDue": 0,
        "derived": {
          "grossLevyRate": 0.01751557,
          "netEffectiveTaxRate": 0.016265749936338173,
          "totalCreditAmount": -490.8
        },
        "sourceNote": "Nebraska Taxes Online statement detail modal.",
        "land": null,
        "dwelling": null,
        "outbuilding": 0
      }
    ],
    "districtLevyHistory": [
      {
        "year": 2025,
        "levy": 1.398364,
        "status": "statement-detail",
        "note": "Listed in the Nebraska Taxes Online tax distribution detail modal."
      },
      {
        "year": 2024,
        "levy": 1.489636,
        "status": "statement-detail",
        "note": "Listed in the Nebraska Taxes Online tax distribution detail modal."
      },
      {
        "year": 2023,
        "levy": 1.639225,
        "status": "statement-detail",
        "note": "Listed in the Nebraska Taxes Online tax distribution detail modal."
      },
      {
        "year": 2022,
        "levy": 1.687121,
        "status": "statement-detail",
        "note": "Listed in the Nebraska Taxes Online tax distribution detail modal."
      },
      {
        "year": 2021,
        "levy": 1.722094,
        "status": "statement-detail",
        "note": "Listed in the Nebraska Taxes Online tax distribution detail modal."
      },
      {
        "year": 2020,
        "levy": 1.722327,
        "status": "statement-detail",
        "note": "Listed in the Nebraska Taxes Online tax distribution detail modal."
      },
      {
        "year": 2019,
        "levy": 1.751557,
        "status": "statement-detail",
        "note": "Listed in the Nebraska Taxes Online tax distribution detail modal."
      }
    ],
    "assessedValueBreakdown": [
      {
        "year": 2025,
        "dwelling": 0,
        "land": 407595,
        "outbuilding": 0,
        "total": 664185,
        "source": "Nebraska Taxes Online detail modal"
      },
      {
        "year": 2024,
        "dwelling": null,
        "land": null,
        "outbuilding": 0,
        "total": 477385,
        "source": "Nebraska Taxes Online detail modal"
      },
      {
        "year": 2023,
        "dwelling": null,
        "land": null,
        "outbuilding": 0,
        "total": 407595,
        "source": "Nebraska Taxes Online detail modal"
      },
      {
        "year": 2022,
        "dwelling": null,
        "land": null,
        "outbuilding": 0,
        "total": 372985,
        "source": "Nebraska Taxes Online detail modal"
      },
      {
        "year": 2021,
        "dwelling": null,
        "land": null,
        "outbuilding": 0,
        "total": 372985,
        "source": "Nebraska Taxes Online detail modal"
      },
      {
        "year": 2020,
        "dwelling": null,
        "land": null,
        "outbuilding": 0,
        "total": 372985,
        "source": "Nebraska Taxes Online detail modal"
      },
      {
        "year": 2019,
        "dwelling": null,
        "land": null,
        "outbuilding": 0,
        "total": 392700,
        "source": "Nebraska Taxes Online detail modal"
      }
    ],
    "latestFinalLevyComponents": [
      {
        "description": "SOUTHERN SCH",
        "rate": 1.012112,
        "amount": 6722.3,
        "share": 72.4,
        "group": "School"
      },
      {
        "description": "COUNTY GENERAL",
        "rate": 0.234958,
        "amount": 1560.54,
        "share": 16.8,
        "group": "County"
      },
      {
        "description": "ISLAND GROVE TWP",
        "rate": 0.050746,
        "amount": 337.05,
        "share": 3.6,
        "group": "Other"
      },
      {
        "description": "BIG BLUE NRD",
        "rate": 0.032155,
        "amount": 213.57,
        "share": 2.3,
        "group": "Natural resources"
      },
      {
        "description": "BLUE SPRINGS FIRE",
        "rate": 0.03,
        "amount": 199.26,
        "share": 2.1,
        "group": "Other"
      },
      {
        "description": "SCC",
        "rate": 0.02,
        "amount": 132.84,
        "share": 1.4,
        "group": "Community college"
      },
      {
        "description": "ESU #5",
        "rate": 0.015,
        "amount": 99.63,
        "share": 1.1,
        "group": "Education service"
      },
      {
        "description": "AG SOCIETY",
        "rate": 0.002759,
        "amount": 18.32,
        "share": 0.2,
        "group": "Other"
      },
      {
        "description": "HISTORICAL SOCIETY",
        "rate": 0.000634,
        "amount": 4.21,
        "share": 0,
        "group": "Other"
      }
    ],
    "dwellingData": [
      {
        "description": "HISTORICAL 0.00082300",
        "units": 1,
        "value": 3273100
      }
    ],
    "outbuildingData": [],
    "propertyNotes": [
      {
        "date": null,
        "note": "Draft generated from GWorks PDF and NTO statement detail captures."
      },
      {
        "date": null,
        "note": "Review photo/sketch assets and any unavailable cost-model detail before publishing."
      }
    ],
    "landInformation": [
      {
        "description": "N/A",
        "squareFeet": null,
        "acres": null,
        "actualFrontFeet": null,
        "effectiveFrontFeet": null,
        "depth": null,
        "recordedValue": 407595,
        "source": "Nebraska Taxes Online detail modal and GWorks PDF classification"
      }
    ],
    "sources": [
      "Gage County Assessor GWorks property report",
      "Nebraska Taxes Online statement detail modal"
    ],
    "sourcePolicy": {
      "primaryFacts": "GWorks PDF",
      "taxStatements": "Nebraska Taxes Online",
      "unavailableFields": "Leave as null/unavailable instead of inferring."
    }
  },
  "parcelIdentifiers": {
    "parcelId": "0003273100",
    "cardFilePerm": null,
    "cadastralId": "4-46-7",
    "padClassCode": null,
    "stateGeo": "4407-05-3-00000-000-0000",
    "appraiserId": null,
    "taxOnlineParcelId": "0003273100"
  },
  "locationModel": {
    "valuationGroup": "Market Area 2",
    "marketArea": "Market Area 2",
    "marketGroup": "Agricultural"
  },
  "landModel": {
    "description": "Land row from GWorks public export",
    "lotSize": "N/A",
    "recordedLotValue": 407595,
    "frontage": null,
    "cutoffSchedule": []
  },
  "currentCardValue": {
    "previous": {
      "buildings": null,
      "improvement": 0,
      "landLots": null,
      "total": 477385
    },
    "current": {
      "buildings": 0,
      "improvement": 0,
      "landLots": 407595,
      "total": 664185,
      "note": "2025 assessed values from GWorks PDF and Nebraska Taxes Online detail modal. PDF latest total: $407,595."
    }
  },
  "ownershipHistory": [],
  "valuationHistory": [
    {
      "year": 2025,
      "total": 407595,
      "land": 407595,
      "outbuilding": 0,
      "dwelling": 0,
      "source": "GWorks PDF"
    }
  ],
  "propertyValuation": {
    "buildings": 0,
    "improvement": 0,
    "landLot": 407595,
    "total": 664185
  },
  "valuationReconciliation": {
    "source": "GWorks public export and Nebraska Taxes Online detail modal",
    "initialMipsTotal": null,
    "finalAssessedTotal": 664185,
    "finalDwellingValue": 0,
    "landLot": 407595,
    "modeledDetailSubtotal": null,
    "cardToFinalAdjustment": null,
    "modelToFinalReconciliation": null,
    "note": "The GWorks export gives value rollups and visible component rows, but not the Marshall & Swift cost/depreciation bridge used by the older MIPS-style card."
  },
  "reviewHistory": [],
  "residentialInformation": {
    "type": "Agricultural",
    "quality": null,
    "condition": "N/A",
    "architecture": null,
    "baseTotalArea": null,
    "style": "N/A",
    "exteriorWall": null,
    "heatingCooling": "Basement Size: 0 sq. ft Min Finish: 0 sq. ft",
    "roofCover": null,
    "areaOfSlab": null,
    "areaOfCrawl": null,
    "fixtureRoughin": "6",
    "bedBathroom": "/",
    "basementArea": null
  },
  "costApproach": {
    "available": false,
    "yearEffectiveAge": null,
    "baseCost": null,
    "adjustments": null,
    "adjustedCost": null,
    "rcn": null,
    "totalMiscImprovements": null,
    "garageCost": null,
    "totalRcn": null,
    "depreciation": {
      "physicalPercent": null,
      "functionalPercent": null,
      "amount": null
    },
    "depreciatedMiscImprovements": null,
    "depreciatedGarages": null,
    "rcnld": null,
    "adjustedRcnld": null,
    "costPerSquareFoot": null,
    "note": "Marshall & Swift-level cost details are not included in this GWorks PDF export."
  },
  "garageCostLines": [],
  "miscImprovements": [
    {
      "description": "HISTORICAL 0.00082300",
      "units": 1,
      "value": 3273100,
      "source": "GWorks PDF dwelling data"
    }
  ],
  "sourceExtract": {
    "note": "Generated from GWorks PDF facts and Nebraska Taxes Online 2019-current statement details. Review unavailable cost-model fields before publishing.",
    "sections": [
      {
        "title": "GWorks Current/Prior Assessed Values",
        "summary": "1 assessment years from the exported PDF",
        "columns": [
          "Year",
          "Total",
          "Land",
          "Outbuilding",
          "Dwelling"
        ],
        "rows": [
          [
            "2025",
            "$407,595",
            "$407,595",
            "$0",
            "$0"
          ]
        ]
      },
      {
        "title": "Nebraska Taxes Online Statement History",
        "summary": "2019-2025 tax statements",
        "columns": [
          "Year",
          "Statement",
          "Type",
          "Gross tax",
          "Credits",
          "Net tax",
          "Total paid",
          "Tax due"
        ],
        "rows": [
          [
            "2025",
            "4625",
            "REAL",
            "$9,287.72",
            "$-2,749.54",
            "$6,538.18",
            "$3,269.09",
            "$3,269.09"
          ],
          [
            "2024",
            "5391",
            "REAL",
            "$7,111.3",
            "$-1,910.7",
            "$5,200.6",
            "$5,200.6",
            "$0"
          ],
          [
            "2023",
            "5378",
            "REAL",
            "$6,681.4",
            "$-544.34",
            "$6,137.06",
            "$6,137.06",
            "$0"
          ],
          [
            "2022",
            "3904",
            "REAL",
            "$6,292.7",
            "$-477.02",
            "$5,815.68",
            "$5,815.68",
            "$0"
          ],
          [
            "2021",
            "3894",
            "REAL",
            "$6,423.16",
            "$-481.34",
            "$5,941.82",
            "$5,941.82",
            "$0"
          ],
          [
            "2020",
            "3874",
            "REAL",
            "$6,424.02",
            "$-457.42",
            "$5,966.6",
            "$5,966.6",
            "$0"
          ],
          [
            "2019",
            "3862",
            "REAL",
            "$6,878.36",
            "$-490.8",
            "$6,387.56",
            "$6,387.56",
            "$0"
          ]
        ]
      },
      {
        "title": " Tax Distribution",
        "summary": "9 authority rows from Nebraska Taxes Online",
        "columns": [
          "Authority / fund",
          "Levy",
          "Amount",
          "Share"
        ],
        "rows": [
          [
            "6101: SOUTHERN SCH",
            "1.012112",
            "$6,722.3",
            "72.4%"
          ],
          [
            "100: COUNTY GENERAL",
            "0.234958",
            "$1,560.54",
            "16.8%"
          ],
          [
            "8813: ISLAND GROVE TWP",
            "0.050746",
            "$337.05",
            "3.6%"
          ],
          [
            "7301: BIG BLUE NRD",
            "0.032155",
            "$213.57",
            "2.3%"
          ],
          [
            "7704: BLUE SPRINGS FIRE",
            "0.030000",
            "$199.26",
            "2.1%"
          ],
          [
            "7100: SCC",
            "0.020000",
            "$132.84",
            "1.4%"
          ],
          [
            "6905: ESU #5",
            "0.015000",
            "$99.63",
            "1.1%"
          ],
          [
            "9200: AG SOCIETY",
            "0.002759",
            "$18.32",
            "0.2%"
          ],
          [
            "9300: HISTORICAL SOCIETY",
            "0.000634",
            "$4.21",
            "0%"
          ]
        ]
      },
      {
        "title": "Residential Datasheet",
        "summary": "Unknown year / unknown sq. ft.",
        "columns": [
          "Field",
          "Value"
        ],
        "rows": [
          [
            "Style",
            "N/A"
          ],
          [
            "Heating/Cooling",
            "Basement Size: 0 sq. ft Min Finish: 0 sq. ft"
          ],
          [
            "Plumbing fixtures",
            "6"
          ],
          [
            "Basement size",
            " sq. ft."
          ],
          [
            "Building size",
            " sq. ft."
          ],
          [
            "Garage 1 size",
            " sq. ft."
          ],
          [
            "Condition",
            "N/A"
          ]
        ]
      },
      {
        "title": "Dwelling Data",
        "summary": "1 visible rows",
        "columns": [
          "Description",
          "Units",
          "Value"
        ],
        "rows": [
          [
            "HISTORICAL 0.00082300",
            "1",
            "$3,273,100"
          ]
        ]
      }
    ]
  }
}
