{
  "source": {
    "sourceType": "property_record",
    "system": "GWorks Public Access",
    "displayCitation": "Gage County Assessor GWorks property report",
    "county": "Gage County",
    "reportName": "Gage County Assessor property report",
    "recordType": "GWORKS_PROPERTY_REPORT",
    "printedAt": null,
    "sourceImages": [
      "assets/images/0003759000_1.jpg",
      "assets/images/0003759000_2.jpg"
    ],
    "sourceImageLinks": [
      "https://gage.gworks.com/photos/0003759000_1.jpg",
      "https://gage.gworks.com/photos/0003759000_2.jpg",
      "https://gage.gworks.com/photos/0003759000_3.jpg",
      "https://gage.gworks.com/photos/0003759000_4.jpg"
    ],
    "notes": "Generated from GWorks PDF facts, with 2019-and-newer tax-statement history, assessed valuation components, credit breakdowns, payment status, and levy distributions added from Nebraska Taxes Online detail captures. The GWorks export does not expose Marshall & Swift cost-source, base-cost, adjustment, depreciation, or RCNLD detail."
  },
  "guidedSnapshot": {
    "snapshotYear": 2025,
    "latestFinalTaxYear": 2025,
    "assets": {
      "photo": "assets/images/0003759000_1.jpg",
      "sketch": "assets/images/0003759000_2.jpg",
      "additionalPhotos": []
    },
    "parcel": {
      "parcelId": "0003759000",
      "mapNumber": "3759000",
      "stateGeoCode": "0000-00-0-70005-002-0000",
      "owner": "SHAW, LARRY A & MARGARET",
      "mailingAddress": "30899 MAIN ST, BEATRICE, NE 68310",
      "situsAddress": "30899 MAIN",
      "countyName": "GAGE",
      "taxDistrict": "87",
      "schoolDistrict": "SCH 15 BEATRICE, 34-0015",
      "accountType": "Residential",
      "legalDescription": "LOTS 1-5 INC BLK 2 ELLIS ORIG"
    },
    "classification": {
      "status": "Improved",
      "location": "Urban",
      "propertyClass": "Residential",
      "citySize": "1-100",
      "zoning": "Single Family",
      "lotSize": "2.50"
    },
    "residential": {
      "style": "100% One Story",
      "yearBuilt": 1981,
      "buildingSize": 1365,
      "basementSize": null,
      "bedrooms": null,
      "bathrooms": null,
      "plumbingFixtures": 5,
      "quality": "Fair",
      "condition": "Average",
      "exterior": "100% Frame, Plywood or Hardboard",
      "heatingCooling": "100% Wall Furnace",
      "garage1": "Attached Garage(SF), 288 sq. ft.",
      "minFinish": 0,
      "partFinish": 0
    },
    "taxpayerHistory": [
      {
        "year": 2025,
        "assessedValue": 97040,
        "taxes": 894.22,
        "status": "partially-paid",
        "assessmentSource": "Nebraska Taxes Online detail modal"
      },
      {
        "year": 2024,
        "assessedValue": 41810,
        "taxes": 418.84,
        "status": "tax-statement",
        "assessmentSource": "Nebraska Taxes Online detail modal"
      },
      {
        "year": 2023,
        "assessedValue": 41810,
        "taxes": 608.46,
        "status": "tax-statement",
        "assessmentSource": "Nebraska Taxes Online detail modal"
      },
      {
        "year": 2022,
        "assessedValue": 41810,
        "taxes": 641.6,
        "status": "tax-statement",
        "assessmentSource": "Nebraska Taxes Online detail modal"
      },
      {
        "year": 2021,
        "assessedValue": 41810,
        "taxes": 658.12,
        "status": "tax-statement",
        "assessmentSource": "Nebraska Taxes Online detail modal"
      },
      {
        "year": 2020,
        "assessedValue": 41810,
        "taxes": 660.56,
        "status": "tax-statement",
        "assessmentSource": "Nebraska Taxes Online detail modal"
      },
      {
        "year": 2019,
        "assessedValue": 41810,
        "taxes": 674.16,
        "status": "tax-statement",
        "assessmentSource": "Nebraska Taxes Online detail modal"
      }
    ],
    "taxStatements": [
      {
        "taxYear": 2025,
        "statementNumber": "13534",
        "statementType": "REAL",
        "totalTaxesDue": 894.22,
        "dueDate": null,
        "assessedValue": 97040,
        "grossTaxAmount": 1246.98,
        "credits": {
          "homestead": {
            "value": 0,
            "amount": 0
          },
          "nonAgTax": {
            "value": null,
            "amount": -115.48
          },
          "agLandTax": {
            "value": null,
            "amount": 0
          },
          "schoolTax": {
            "value": null,
            "amount": -237.28
          }
        },
        "netAmountDue": 894.22,
        "totalPaid": 447.11,
        "taxDue": 447.11,
        "derived": {
          "grossLevyRate": 0.01285019,
          "netEffectiveTaxRate": 0.009214962901896126,
          "totalCreditAmount": -352.76
        },
        "sourceNote": "Nebraska Taxes Online statement detail modal.",
        "land": 665,
        "dwelling": 79195,
        "outbuilding": 17180
      },
      {
        "taxYear": 2024,
        "statementNumber": "14632",
        "statementType": "REAL",
        "totalTaxesDue": 418.84,
        "dueDate": null,
        "assessedValue": 41810,
        "grossTaxAmount": 590.5,
        "credits": {
          "homestead": {
            "value": 0,
            "amount": 0
          },
          "nonAgTax": {
            "value": null,
            "amount": -50.1
          },
          "agLandTax": {
            "value": null,
            "amount": 0
          },
          "schoolTax": {
            "value": null,
            "amount": -121.56
          }
        },
        "netAmountDue": 418.84,
        "totalPaid": 418.84,
        "taxDue": 0,
        "derived": {
          "grossLevyRate": 0.01412336,
          "netEffectiveTaxRate": 0.010017699115044246,
          "totalCreditAmount": -171.66
        },
        "sourceNote": "Nebraska Taxes Online statement detail modal.",
        "land": 125,
        "dwelling": 41685,
        "outbuilding": 0
      },
      {
        "taxYear": 2023,
        "statementNumber": "14587",
        "statementType": "REAL",
        "totalTaxesDue": 608.46,
        "dueDate": null,
        "assessedValue": 41810,
        "grossTaxAmount": 655,
        "credits": {
          "homestead": {
            "value": 0,
            "amount": 0
          },
          "nonAgTax": {
            "value": null,
            "amount": -46.54
          },
          "agLandTax": {
            "value": null,
            "amount": 0
          },
          "schoolTax": {
            "value": null,
            "amount": 0
          }
        },
        "netAmountDue": 608.46,
        "totalPaid": 608.46,
        "taxDue": 0,
        "derived": {
          "grossLevyRate": 0.01566585,
          "netEffectiveTaxRate": 0.014552977756517581,
          "totalCreditAmount": -46.54
        },
        "sourceNote": "Nebraska Taxes Online statement detail modal.",
        "land": 125,
        "dwelling": 41685,
        "outbuilding": 0
      },
      {
        "taxYear": 2022,
        "statementNumber": "4449",
        "statementType": "REAL",
        "totalTaxesDue": 641.6,
        "dueDate": null,
        "assessedValue": 41810,
        "grossTaxAmount": 686.16,
        "credits": {
          "homestead": {
            "value": 0,
            "amount": 0
          },
          "nonAgTax": {
            "value": null,
            "amount": -44.56
          },
          "agLandTax": {
            "value": null,
            "amount": 0
          },
          "schoolTax": {
            "value": null,
            "amount": 0
          }
        },
        "netAmountDue": 641.6,
        "totalPaid": 641.6,
        "taxDue": 0,
        "derived": {
          "grossLevyRate": 0.01641128,
          "netEffectiveTaxRate": 0.015345611097823487,
          "totalCreditAmount": -44.56
        },
        "sourceNote": "Nebraska Taxes Online statement detail modal.",
        "land": 125,
        "dwelling": 41685,
        "outbuilding": 0
      },
      {
        "taxYear": 2021,
        "statementNumber": "4440",
        "statementType": "REAL",
        "totalTaxesDue": 658.12,
        "dueDate": null,
        "assessedValue": 41810,
        "grossTaxAmount": 703.08,
        "credits": {
          "homestead": {
            "value": 0,
            "amount": 0
          },
          "nonAgTax": {
            "value": null,
            "amount": -44.96
          },
          "agLandTax": {
            "value": null,
            "amount": 0
          },
          "schoolTax": {
            "value": null,
            "amount": 0
          }
        },
        "netAmountDue": 658.12,
        "totalPaid": 658.12,
        "taxDue": 0,
        "derived": {
          "grossLevyRate": 0.01681601,
          "netEffectiveTaxRate": 0.015740731882324804,
          "totalCreditAmount": -44.96
        },
        "sourceNote": "Nebraska Taxes Online statement detail modal.",
        "land": 125,
        "dwelling": 41685,
        "outbuilding": 0
      },
      {
        "taxYear": 2020,
        "statementNumber": "4417",
        "statementType": "REAL",
        "totalTaxesDue": 660.56,
        "dueDate": null,
        "assessedValue": 41810,
        "grossTaxAmount": 703.3,
        "credits": {
          "homestead": {
            "value": 0,
            "amount": 0
          },
          "nonAgTax": {
            "value": null,
            "amount": -42.74
          },
          "agLandTax": {
            "value": null,
            "amount": 0
          },
          "schoolTax": {
            "value": null,
            "amount": 0
          }
        },
        "netAmountDue": 660.56,
        "totalPaid": 660.56,
        "taxDue": 0,
        "derived": {
          "grossLevyRate": 0.0168212,
          "netEffectiveTaxRate": 0.015799091126524754,
          "totalCreditAmount": -42.74
        },
        "sourceNote": "Nebraska Taxes Online statement detail modal.",
        "land": 125,
        "dwelling": 41685,
        "outbuilding": 0
      },
      {
        "taxYear": 2019,
        "statementNumber": "4402",
        "statementType": "REAL",
        "totalTaxesDue": 674.16,
        "dueDate": null,
        "assessedValue": 41810,
        "grossTaxAmount": 717.7,
        "credits": {
          "homestead": {
            "value": 0,
            "amount": 0
          },
          "nonAgTax": {
            "value": null,
            "amount": -43.54
          },
          "agLandTax": {
            "value": null,
            "amount": 0
          },
          "schoolTax": {
            "value": null,
            "amount": 0
          }
        },
        "netAmountDue": 674.16,
        "totalPaid": 674.16,
        "taxDue": 0,
        "derived": {
          "grossLevyRate": 0.017165859999999998,
          "netEffectiveTaxRate": 0.01612437215977039,
          "totalCreditAmount": -43.54
        },
        "sourceNote": "Nebraska Taxes Online statement detail modal.",
        "land": 125,
        "dwelling": 41685,
        "outbuilding": 0
      }
    ],
    "districtLevyHistory": [
      {
        "year": 2025,
        "levy": 1.285019,
        "status": "statement-detail",
        "note": "Listed in the Nebraska Taxes Online tax distribution detail modal."
      },
      {
        "year": 2024,
        "levy": 1.412336,
        "status": "statement-detail",
        "note": "Listed in the Nebraska Taxes Online tax distribution detail modal."
      },
      {
        "year": 2023,
        "levy": 1.566585,
        "status": "statement-detail",
        "note": "Listed in the Nebraska Taxes Online tax distribution detail modal."
      },
      {
        "year": 2022,
        "levy": 1.641128,
        "status": "statement-detail",
        "note": "Listed in the Nebraska Taxes Online tax distribution detail modal."
      },
      {
        "year": 2021,
        "levy": 1.681601,
        "status": "statement-detail",
        "note": "Listed in the Nebraska Taxes Online tax distribution detail modal."
      },
      {
        "year": 2020,
        "levy": 1.68212,
        "status": "statement-detail",
        "note": "Listed in the Nebraska Taxes Online tax distribution detail modal."
      },
      {
        "year": 2019,
        "levy": 1.716586,
        "status": "statement-detail",
        "note": "Listed in the Nebraska Taxes Online tax distribution detail modal."
      }
    ],
    "assessedValueBreakdown": [
      {
        "year": 2025,
        "dwelling": 79195,
        "land": 665,
        "outbuilding": 17180,
        "total": 97040,
        "source": "Nebraska Taxes Online detail modal"
      },
      {
        "year": 2024,
        "dwelling": 41685,
        "land": 125,
        "outbuilding": 0,
        "total": 41810,
        "source": "Nebraska Taxes Online detail modal"
      },
      {
        "year": 2023,
        "dwelling": 41685,
        "land": 125,
        "outbuilding": 0,
        "total": 41810,
        "source": "Nebraska Taxes Online detail modal"
      },
      {
        "year": 2022,
        "dwelling": 41685,
        "land": 125,
        "outbuilding": 0,
        "total": 41810,
        "source": "Nebraska Taxes Online detail modal"
      },
      {
        "year": 2021,
        "dwelling": 41685,
        "land": 125,
        "outbuilding": 0,
        "total": 41810,
        "source": "Nebraska Taxes Online detail modal"
      },
      {
        "year": 2020,
        "dwelling": 41685,
        "land": 125,
        "outbuilding": 0,
        "total": 41810,
        "source": "Nebraska Taxes Online detail modal"
      },
      {
        "year": 2019,
        "dwelling": 41685,
        "land": 125,
        "outbuilding": 0,
        "total": 41810,
        "source": "Nebraska Taxes Online detail modal"
      }
    ],
    "latestFinalLevyComponents": [
      {
        "description": "BEATRICE SCH",
        "rate": 0.912565,
        "amount": 885.55,
        "share": 71,
        "group": "School"
      },
      {
        "description": "COUNTY GENERAL",
        "rate": 0.234958,
        "amount": 228,
        "share": 18.3,
        "group": "County"
      },
      {
        "description": "LINCOLN TOWNSHIP",
        "rate": 0.036948,
        "amount": 35.85,
        "share": 2.9,
        "group": "Other"
      },
      {
        "description": "BIG BLUE NRD",
        "rate": 0.032155,
        "amount": 31.2,
        "share": 2.5,
        "group": "Natural resources"
      },
      {
        "description": "BEATRICE FIRE",
        "rate": 0.03,
        "amount": 29.11,
        "share": 2.3,
        "group": "Other"
      },
      {
        "description": "SCC",
        "rate": 0.02,
        "amount": 19.41,
        "share": 1.6,
        "group": "Community college"
      },
      {
        "description": "ESU #5",
        "rate": 0.015,
        "amount": 14.56,
        "share": 1.2,
        "group": "Education service"
      },
      {
        "description": "AG SOCIETY",
        "rate": 0.002759,
        "amount": 2.68,
        "share": 0.2,
        "group": "Other"
      },
      {
        "description": "HISTORICAL SOCIETY",
        "rate": 0.000634,
        "amount": 0.62,
        "share": 0,
        "group": "Other"
      }
    ],
    "dwellingData": [
      {
        "description": "SLAB W/ROOF",
        "units": 45,
        "value": 770
      },
      {
        "description": "OPEN PORCH W/ROOF",
        "units": 210,
        "value": 2915
      }
    ],
    "outbuildingData": [],
    "propertyNotes": [
      {
        "date": null,
        "note": "Draft generated from GWorks PDF and NTO statement detail captures."
      },
      {
        "date": null,
        "note": "Review photo/sketch assets and any unavailable cost-model detail before publishing."
      }
    ],
    "landInformation": [
      {
        "description": "2.50",
        "squareFeet": null,
        "acres": null,
        "actualFrontFeet": null,
        "effectiveFrontFeet": null,
        "depth": null,
        "recordedValue": 665,
        "source": "Nebraska Taxes Online detail modal and GWorks PDF classification"
      }
    ],
    "sources": [
      "Gage County Assessor GWorks property report",
      "Nebraska Taxes Online statement detail modal"
    ],
    "sourcePolicy": {
      "primaryFacts": "GWorks PDF",
      "taxStatements": "Nebraska Taxes Online",
      "unavailableFields": "Leave as null/unavailable instead of inferring."
    }
  },
  "parcelIdentifiers": {
    "parcelId": "0003759000",
    "cardFilePerm": null,
    "cadastralId": "2-35-13",
    "padClassCode": null,
    "stateGeo": "0000-00-0-70005-002-0000",
    "appraiserId": null,
    "taxOnlineParcelId": "0003759000"
  },
  "locationModel": {
    "valuationGroup": "13 - Rockford, Holmesville, Lanham, Ellis",
    "marketArea": "Rockford, Holmesville, Lanham, Ellis",
    "marketGroup": "Unincorporated"
  },
  "landModel": {
    "description": "Land row from GWorks public export",
    "lotSize": "2.50",
    "recordedLotValue": 665,
    "frontage": null,
    "cutoffSchedule": []
  },
  "currentCardValue": {
    "previous": {
      "buildings": 41685,
      "improvement": 0,
      "landLots": 125,
      "total": 41810
    },
    "current": {
      "buildings": 79195,
      "improvement": 17180,
      "landLots": 665,
      "total": 97040,
      "note": "2025 assessed values from GWorks PDF and Nebraska Taxes Online detail modal. PDF latest total: $41,810."
    }
  },
  "ownershipHistory": [],
  "valuationHistory": [
    {
      "year": 2025,
      "total": 41810,
      "land": 125,
      "outbuilding": 0,
      "dwelling": 41685,
      "source": "GWorks PDF"
    }
  ],
  "propertyValuation": {
    "buildings": 79195,
    "improvement": 17180,
    "landLot": 665,
    "total": 97040
  },
  "valuationReconciliation": {
    "source": "GWorks public export and Nebraska Taxes Online detail modal",
    "initialMipsTotal": null,
    "finalAssessedTotal": 97040,
    "finalDwellingValue": 79195,
    "landLot": 665,
    "modeledDetailSubtotal": null,
    "cardToFinalAdjustment": null,
    "modelToFinalReconciliation": null,
    "note": "The GWorks export gives value rollups and visible component rows, but not the Marshall & Swift cost/depreciation bridge used by the older MIPS-style card."
  },
  "reviewHistory": [],
  "residentialInformation": {
    "type": "Single Family",
    "quality": "Fair",
    "condition": "Average",
    "architecture": null,
    "baseTotalArea": "1,365",
    "style": "100% One Story",
    "exteriorWall": "100% Frame, Plywood or Hardboard",
    "heatingCooling": "100% Wall Furnace",
    "roofCover": null,
    "areaOfSlab": null,
    "areaOfCrawl": null,
    "fixtureRoughin": "5",
    "bedBathroom": "/",
    "basementArea": null
  },
  "costApproach": {
    "available": false,
    "yearEffectiveAge": null,
    "baseCost": null,
    "adjustments": null,
    "adjustedCost": null,
    "rcn": null,
    "totalMiscImprovements": null,
    "garageCost": null,
    "totalRcn": null,
    "depreciation": {
      "physicalPercent": null,
      "functionalPercent": null,
      "amount": null
    },
    "depreciatedMiscImprovements": null,
    "depreciatedGarages": null,
    "rcnld": null,
    "adjustedRcnld": null,
    "costPerSquareFoot": null,
    "note": "Marshall & Swift-level cost details are not included in this GWorks PDF export."
  },
  "garageCostLines": [
    {
      "description": "Attached Garage(SF)",
      "units": 288,
      "value": null,
      "source": "GWorks PDF residential datasheet"
    }
  ],
  "miscImprovements": [
    {
      "description": "SLAB W/ROOF",
      "units": 45,
      "value": 770,
      "source": "GWorks PDF dwelling data"
    },
    {
      "description": "OPEN PORCH W/ROOF",
      "units": 210,
      "value": 2915,
      "source": "GWorks PDF dwelling data"
    }
  ],
  "sourceExtract": {
    "note": "Generated from GWorks PDF facts and Nebraska Taxes Online 2019-current statement details. Review unavailable cost-model fields before publishing.",
    "sections": [
      {
        "title": "GWorks Current/Prior Assessed Values",
        "summary": "1 assessment years from the exported PDF",
        "columns": [
          "Year",
          "Total",
          "Land",
          "Outbuilding",
          "Dwelling"
        ],
        "rows": [
          [
            "2025",
            "$41,810",
            "$125",
            "$0",
            "$41,685"
          ]
        ]
      },
      {
        "title": "Nebraska Taxes Online Statement History",
        "summary": "2019-2025 tax statements",
        "columns": [
          "Year",
          "Statement",
          "Type",
          "Gross tax",
          "Credits",
          "Net tax",
          "Total paid",
          "Tax due"
        ],
        "rows": [
          [
            "2025",
            "13534",
            "REAL",
            "$1,246.98",
            "$-352.76",
            "$894.22",
            "$447.11",
            "$447.11"
          ],
          [
            "2024",
            "14632",
            "REAL",
            "$590.5",
            "$-171.66",
            "$418.84",
            "$418.84",
            "$0"
          ],
          [
            "2023",
            "14587",
            "REAL",
            "$655",
            "$-46.54",
            "$608.46",
            "$608.46",
            "$0"
          ],
          [
            "2022",
            "4449",
            "REAL",
            "$686.16",
            "$-44.56",
            "$641.6",
            "$641.6",
            "$0"
          ],
          [
            "2021",
            "4440",
            "REAL",
            "$703.08",
            "$-44.96",
            "$658.12",
            "$658.12",
            "$0"
          ],
          [
            "2020",
            "4417",
            "REAL",
            "$703.3",
            "$-42.74",
            "$660.56",
            "$660.56",
            "$0"
          ],
          [
            "2019",
            "4402",
            "REAL",
            "$717.7",
            "$-43.54",
            "$674.16",
            "$674.16",
            "$0"
          ]
        ]
      },
      {
        "title": " Tax Distribution",
        "summary": "9 authority rows from Nebraska Taxes Online",
        "columns": [
          "Authority / fund",
          "Levy",
          "Amount",
          "Share"
        ],
        "rows": [
          [
            "6115: BEATRICE SCH",
            "0.912565",
            "$885.55",
            "71%"
          ],
          [
            "100: COUNTY GENERAL",
            "0.234958",
            "$228",
            "18.3%"
          ],
          [
            "8815: LINCOLN TOWNSHIP",
            "0.036948",
            "$35.85",
            "2.9%"
          ],
          [
            "7301: BIG BLUE NRD",
            "0.032155",
            "$31.2",
            "2.5%"
          ],
          [
            "7701: BEATRICE FIRE",
            "0.030000",
            "$29.11",
            "2.3%"
          ],
          [
            "7100: SCC",
            "0.020000",
            "$19.41",
            "1.6%"
          ],
          [
            "6905: ESU #5",
            "0.015000",
            "$14.56",
            "1.2%"
          ],
          [
            "9200: AG SOCIETY",
            "0.002759",
            "$2.68",
            "0.2%"
          ],
          [
            "9300: HISTORICAL SOCIETY",
            "0.000634",
            "$0.62",
            "0%"
          ]
        ]
      },
      {
        "title": "Residential Datasheet",
        "summary": "1981 / 1,365 sq. ft.",
        "columns": [
          "Field",
          "Value"
        ],
        "rows": [
          [
            "Zoning",
            "Single Family"
          ],
          [
            "Style",
            "100% One Story"
          ],
          [
            "Year built",
            "1981"
          ],
          [
            "Exterior",
            "100% Frame, Plywood or Hardboard"
          ],
          [
            "Heating/Cooling",
            "100% Wall Furnace"
          ],
          [
            "Plumbing fixtures",
            "5"
          ],
          [
            "Basement size",
            " sq. ft."
          ],
          [
            "Building size",
            "1365 sq. ft."
          ],
          [
            "Garage 1",
            "Attached Garage(SF)"
          ],
          [
            "Garage 1 size",
            "288 sq. ft."
          ],
          [
            "Quality",
            "Fair"
          ],
          [
            "Condition",
            "Average"
          ]
        ]
      },
      {
        "title": "Dwelling Data",
        "summary": "2 visible rows",
        "columns": [
          "Description",
          "Units",
          "Value"
        ],
        "rows": [
          [
            "SLAB W/ROOF",
            "45",
            "$770"
          ],
          [
            "OPEN PORCH W/ROOF",
            "210",
            "$2,915"
          ]
        ]
      }
    ]
  }
}
